<?xml version="1.0" encoding="UTF-8"?>
<!DOCTYPE LCTL_TEXT SYSTEM "ltf.v1.5.dtd">
<LCTL_TEXT>
<DOC id="2000_sentences">
<TEXT>
<SEG end_char="300158" id="2000_sentences-1057" start_char="299958">
				<ORIGINAL_TEXT>(Világgazdaság: Profitra számít a Synergon, Metro: Százmilliós üzlet, Magyar Hírlap: GPRS-t épít a Synergon a Vodafone-nak, Népszava: Synergon: 100 millió forintos megrendelés a Vodafontól, január 18.)</ORIGINAL_TEXT>
				<TOKEN end_char="299958" id="2000_sentences-1057-0" start_char="299958">(</TOKEN>
				<TOKEN end_char="299971" id="2000_sentences-1057-1" start_char="299959">Világgazdaság</TOKEN>
				<TOKEN end_char="299972" id="2000_sentences-1057-2" start_char="299972">:</TOKEN>
				<TOKEN end_char="299981" id="2000_sentences-1057-3" start_char="299974">Profitra</TOKEN>
				<TOKEN end_char="299988" id="2000_sentences-1057-4" start_char="299983">számít</TOKEN>
				<TOKEN end_char="299990" id="2000_sentences-1057-5" start_char="299990">a</TOKEN>
				<TOKEN end_char="299999" id="2000_sentences-1057-6" start_char="299992">Synergon</TOKEN>
				<TOKEN end_char="300000" id="2000_sentences-1057-7" start_char="300000">,</TOKEN>
				<TOKEN end_char="300006" id="2000_sentences-1057-8" start_char="300002">Metro</TOKEN>
				<TOKEN end_char="300007" id="2000_sentences-1057-9" start_char="300007">:</TOKEN>
				<TOKEN end_char="300019" id="2000_sentences-1057-10" start_char="300009">Százmilliós</TOKEN>
				<TOKEN end_char="300025" id="2000_sentences-1057-11" start_char="300021">üzlet</TOKEN>
				<TOKEN end_char="300026" id="2000_sentences-1057-12" start_char="300026">,</TOKEN>
				<TOKEN end_char="300033" id="2000_sentences-1057-13" start_char="300028">Magyar</TOKEN>
				<TOKEN end_char="300040" id="2000_sentences-1057-14" start_char="300035">Hírlap</TOKEN>
				<TOKEN end_char="300041" id="2000_sentences-1057-15" start_char="300041">:</TOKEN>
				<TOKEN end_char="300046" id="2000_sentences-1057-16" start_char="300043">GPRS</TOKEN>
				<TOKEN end_char="300047" id="2000_sentences-1057-17" start_char="300047">-</TOKEN>
				<TOKEN end_char="300048" id="2000_sentences-1057-18" start_char="300048">t</TOKEN>
				<TOKEN end_char="300053" id="2000_sentences-1057-19" start_char="300050">épít</TOKEN>
				<TOKEN end_char="300055" id="2000_sentences-1057-20" start_char="300055">a</TOKEN>
				<TOKEN end_char="300064" id="2000_sentences-1057-21" start_char="300057">Synergon</TOKEN>
				<TOKEN end_char="300066" id="2000_sentences-1057-22" start_char="300066">a</TOKEN>
				<TOKEN end_char="300075" id="2000_sentences-1057-23" start_char="300068">Vodafone</TOKEN>
				<TOKEN end_char="300076" id="2000_sentences-1057-24" start_char="300076">-</TOKEN>
				<TOKEN end_char="300079" id="2000_sentences-1057-25" start_char="300077">nak</TOKEN>
				<TOKEN end_char="300080" id="2000_sentences-1057-26" start_char="300080">,</TOKEN>
				<TOKEN end_char="300089" id="2000_sentences-1057-27" start_char="300082">Népszava</TOKEN>
				<TOKEN end_char="300090" id="2000_sentences-1057-28" start_char="300090">:</TOKEN>
				<TOKEN end_char="300099" id="2000_sentences-1057-29" start_char="300092">Synergon</TOKEN>
				<TOKEN end_char="300100" id="2000_sentences-1057-30" start_char="300100">:</TOKEN>
				<TOKEN end_char="300104" id="2000_sentences-1057-31" start_char="300102">100</TOKEN>
				<TOKEN end_char="300111" id="2000_sentences-1057-32" start_char="300106">millió</TOKEN>
				<TOKEN end_char="300120" id="2000_sentences-1057-33" start_char="300113">forintos</TOKEN>
				<TOKEN end_char="300132" id="2000_sentences-1057-34" start_char="300122">megrendelés</TOKEN>
				<TOKEN end_char="300134" id="2000_sentences-1057-35" start_char="300134">a</TOKEN>
				<TOKEN end_char="300145" id="2000_sentences-1057-36" start_char="300136">Vodafontól</TOKEN>
				<TOKEN end_char="300146" id="2000_sentences-1057-37" start_char="300146">,</TOKEN>
				<TOKEN end_char="300153" id="2000_sentences-1057-38" start_char="300148">január</TOKEN>
				<TOKEN end_char="300156" id="2000_sentences-1057-39" start_char="300155">18</TOKEN>
				<TOKEN end_char="300157" id="2000_sentences-1057-40" start_char="300157">.</TOKEN>
				<TOKEN end_char="300158" id="2000_sentences-1057-41" start_char="300158">)</TOKEN>
			</SEG>
			</TEXT>
</DOC>
</LCTL_TEXT>