<?xml version="1.0" encoding="UTF-8"?>
<!DOCTYPE LCTL_TEXT SYSTEM "ltf.v1.5.dtd">
<LCTL_TEXT>
<DOC id="2000_sentences">
<TEXT>
<SEG end_char="447048" id="2000_sentences-1652" start_char="446732">
				<ORIGINAL_TEXT>Szakértők szerint a lengyel távközlési piac robbanásszerű növekedését csak a szabályozási hiányosságok gátolják. Lengyelországban ugyanis még mindig a korábbi monopolszolgáltató, a TPSA-é a helyi hívások piacának 95 százaléka, s többségi, 66 százalékos tulajdonosa az egyik vezető mobilszolgáltatónak, a Centertelnek.</ORIGINAL_TEXT>
				<TOKEN end_char="446740" id="2000_sentences-1652-0" start_char="446732">Szakértők</TOKEN>
				<TOKEN end_char="446748" id="2000_sentences-1652-1" start_char="446742">szerint</TOKEN>
				<TOKEN end_char="446750" id="2000_sentences-1652-2" start_char="446750">a</TOKEN>
				<TOKEN end_char="446758" id="2000_sentences-1652-3" start_char="446752">lengyel</TOKEN>
				<TOKEN end_char="446769" id="2000_sentences-1652-4" start_char="446760">távközlési</TOKEN>
				<TOKEN end_char="446774" id="2000_sentences-1652-5" start_char="446771">piac</TOKEN>
				<TOKEN end_char="446788" id="2000_sentences-1652-6" start_char="446776">robbanásszerű</TOKEN>
				<TOKEN end_char="446800" id="2000_sentences-1652-7" start_char="446790">növekedését</TOKEN>
				<TOKEN end_char="446805" id="2000_sentences-1652-8" start_char="446802">csak</TOKEN>
				<TOKEN end_char="446807" id="2000_sentences-1652-9" start_char="446807">a</TOKEN>
				<TOKEN end_char="446820" id="2000_sentences-1652-10" start_char="446809">szabályozási</TOKEN>
				<TOKEN end_char="446833" id="2000_sentences-1652-11" start_char="446822">hiányosságok</TOKEN>
				<TOKEN end_char="446842" id="2000_sentences-1652-12" start_char="446835">gátolják</TOKEN>
				<TOKEN end_char="446843" id="2000_sentences-1652-13" start_char="446843">.</TOKEN>
				<TOKEN end_char="446860" id="2000_sentences-1652-14" start_char="446845">Lengyelországban</TOKEN>
				<TOKEN end_char="446868" id="2000_sentences-1652-15" start_char="446862">ugyanis</TOKEN>
				<TOKEN end_char="446872" id="2000_sentences-1652-16" start_char="446870">még</TOKEN>
				<TOKEN end_char="446879" id="2000_sentences-1652-17" start_char="446874">mindig</TOKEN>
				<TOKEN end_char="446881" id="2000_sentences-1652-18" start_char="446881">a</TOKEN>
				<TOKEN end_char="446889" id="2000_sentences-1652-19" start_char="446883">korábbi</TOKEN>
				<TOKEN end_char="446908" id="2000_sentences-1652-20" start_char="446891">monopolszolgáltató</TOKEN>
				<TOKEN end_char="446909" id="2000_sentences-1652-21" start_char="446909">,</TOKEN>
				<TOKEN end_char="446911" id="2000_sentences-1652-22" start_char="446911">a</TOKEN>
				<TOKEN end_char="446916" id="2000_sentences-1652-23" start_char="446913">TPSA</TOKEN>
				<TOKEN end_char="446917" id="2000_sentences-1652-24" start_char="446917">-</TOKEN>
				<TOKEN end_char="446918" id="2000_sentences-1652-25" start_char="446918">é</TOKEN>
				<TOKEN end_char="446920" id="2000_sentences-1652-26" start_char="446920">a</TOKEN>
				<TOKEN end_char="446926" id="2000_sentences-1652-27" start_char="446922">helyi</TOKEN>
				<TOKEN end_char="446934" id="2000_sentences-1652-28" start_char="446928">hívások</TOKEN>
				<TOKEN end_char="446943" id="2000_sentences-1652-29" start_char="446936">piacának</TOKEN>
				<TOKEN end_char="446946" id="2000_sentences-1652-30" start_char="446945">95</TOKEN>
				<TOKEN end_char="446956" id="2000_sentences-1652-31" start_char="446948">százaléka</TOKEN>
				<TOKEN end_char="446957" id="2000_sentences-1652-32" start_char="446957">,</TOKEN>
				<TOKEN end_char="446959" id="2000_sentences-1652-33" start_char="446959">s</TOKEN>
				<TOKEN end_char="446968" id="2000_sentences-1652-34" start_char="446961">többségi</TOKEN>
				<TOKEN end_char="446969" id="2000_sentences-1652-35" start_char="446969">,</TOKEN>
				<TOKEN end_char="446972" id="2000_sentences-1652-36" start_char="446971">66</TOKEN>
				<TOKEN end_char="446983" id="2000_sentences-1652-37" start_char="446974">százalékos</TOKEN>
				<TOKEN end_char="446995" id="2000_sentences-1652-38" start_char="446985">tulajdonosa</TOKEN>
				<TOKEN end_char="446998" id="2000_sentences-1652-39" start_char="446997">az</TOKEN>
				<TOKEN end_char="447004" id="2000_sentences-1652-40" start_char="447000">egyik</TOKEN>
				<TOKEN end_char="447011" id="2000_sentences-1652-41" start_char="447006">vezető</TOKEN>
				<TOKEN end_char="447031" id="2000_sentences-1652-42" start_char="447013">mobilszolgáltatónak</TOKEN>
				<TOKEN end_char="447032" id="2000_sentences-1652-43" start_char="447032">,</TOKEN>
				<TOKEN end_char="447034" id="2000_sentences-1652-44" start_char="447034">a</TOKEN>
				<TOKEN end_char="447047" id="2000_sentences-1652-45" start_char="447036">Centertelnek</TOKEN>
				<TOKEN end_char="447048" id="2000_sentences-1652-46" start_char="447048">.</TOKEN>
			</SEG>
			</TEXT>
</DOC>
</LCTL_TEXT>