<?xml version="1.0" encoding="UTF-8"?>
<!DOCTYPE LCTL_TEXT SYSTEM "ltf.v1.5.dtd">
<LCTL_TEXT>
<DOC id="NW_WSJ_ENG_0184_20060331.hun">
<TEXT>
<SEG id="NW_WSJ_ENG_0184_20060331.hun-82">
<ORIGINAL_TEXT>Azonban Panamába repült, hogy megszidja Torrijos diktátort a panamai tisztviselők, köztük Noriega drogos kapcsolatai miatt.</ORIGINAL_TEXT>
  <TOKEN id="NW_WSJ_ENG_0184_20060331.hun-82-0">Azonban</TOKEN>
  <TOKEN id="NW_WSJ_ENG_0184_20060331.hun-82-1">Panamába</TOKEN>
  <TOKEN id="NW_WSJ_ENG_0184_20060331.hun-82-2">repült</TOKEN>
  <TOKEN attach="LEFT" id="NW_WSJ_ENG_0184_20060331.hun-82-3">,</TOKEN>
  <TOKEN id="NW_WSJ_ENG_0184_20060331.hun-82-4">hogy</TOKEN>
  <TOKEN id="NW_WSJ_ENG_0184_20060331.hun-82-5">megszidja</TOKEN>
  <TOKEN id="NW_WSJ_ENG_0184_20060331.hun-82-6">Torrijos</TOKEN>
  <TOKEN id="NW_WSJ_ENG_0184_20060331.hun-82-7">diktátort</TOKEN>
  <TOKEN id="NW_WSJ_ENG_0184_20060331.hun-82-8">a</TOKEN>
  <TOKEN id="NW_WSJ_ENG_0184_20060331.hun-82-9">panamai</TOKEN>
  <TOKEN id="NW_WSJ_ENG_0184_20060331.hun-82-10">tisztviselők</TOKEN>
  <TOKEN attach="LEFT" id="NW_WSJ_ENG_0184_20060331.hun-82-11">,</TOKEN>
  <TOKEN id="NW_WSJ_ENG_0184_20060331.hun-82-12">köztük</TOKEN>
  <TOKEN id="NW_WSJ_ENG_0184_20060331.hun-82-13">Noriega</TOKEN>
  <TOKEN id="NW_WSJ_ENG_0184_20060331.hun-82-14">drogos</TOKEN>
  <TOKEN id="NW_WSJ_ENG_0184_20060331.hun-82-15">kapcsolatai</TOKEN>
  <TOKEN id="NW_WSJ_ENG_0184_20060331.hun-82-16">miatt</TOKEN>
  <TOKEN attach="LEFT" id="NW_WSJ_ENG_0184_20060331.hun-82-17">.</TOKEN>
</SEG>
</TEXT>
</DOC>
</LCTL_TEXT>