<?xml version="1.0" encoding="UTF-8"?>
<!DOCTYPE LCTL_TEXT SYSTEM "ltf.v1.5.dtd">
<LCTL_TEXT>
<DOC id="NW_VOA_HAU_003740_20131129">
<TEXT>
<SEG end_char="1802" id="segment-16" start_char="1719">
<ORIGINAL_TEXT>Hakanan kuma zaʼa iya yin amfani da allurar rigakafi mai inganci domin samun kariya.</ORIGINAL_TEXT>
<TOKEN end_char="1725" id="token-16-0" morph="none" pos="word" start_char="1719">Hakanan</TOKEN>
<TOKEN end_char="1730" id="token-16-1" morph="none" pos="word" start_char="1727">kuma</TOKEN>
<TOKEN end_char="1735" id="token-16-2" morph="none" pos="word" start_char="1732">zaʼa</TOKEN>
<TOKEN end_char="1739" id="token-16-3" morph="none" pos="word" start_char="1737">iya</TOKEN>
<TOKEN end_char="1743" id="token-16-4" morph="none" pos="word" start_char="1741">yin</TOKEN>
<TOKEN end_char="1750" id="token-16-5" morph="none" pos="word" start_char="1745">amfani</TOKEN>
<TOKEN end_char="1753" id="token-16-6" morph="none" pos="word" start_char="1752">da</TOKEN>
<TOKEN end_char="1761" id="token-16-7" morph="none" pos="word" start_char="1755">allurar</TOKEN>
<TOKEN end_char="1770" id="token-16-8" morph="none" pos="word" start_char="1763">rigakafi</TOKEN>
<TOKEN end_char="1774" id="token-16-9" morph="none" pos="word" start_char="1772">mai</TOKEN>
<TOKEN end_char="1782" id="token-16-10" morph="none" pos="word" start_char="1776">inganci</TOKEN>
<TOKEN end_char="1788" id="token-16-11" morph="none" pos="word" start_char="1784">domin</TOKEN>
<TOKEN end_char="1794" id="token-16-12" morph="none" pos="word" start_char="1790">samun</TOKEN>
<TOKEN end_char="1801" id="token-16-13" morph="none" pos="word" start_char="1796">kariya</TOKEN>
<TOKEN end_char="1802" id="token-16-14" morph="none" pos="punct" start_char="1802">.</TOKEN>
</SEG>
</TEXT>
</DOC>
</LCTL_TEXT>