<?xml version="1.0" encoding="UTF-8"?>
<!DOCTYPE LCTL_ANNOTATIONS SYSTEM "laf.v1.2.dtd">
<LCTL_ANNOTATIONS lang="UZB">
  <DOC id="NW_OZO_UZB_031264_20140900" lang="UZB">
    <ANNOTATION id="NW_OZO_UZB_031264_20140900-NE1" task="NE">
      <EXTENT start_char="270" end_char="287">Ravshanbek Vafoyev</EXTENT>
      <TAG>PER</TAG>
    </ANNOTATION>
    <ANNOTATION id="NW_OZO_UZB_031264_20140900-NE2" task="NE">
      <EXTENT start_char="290" end_char="308">Abdulaziz Dadaxonov</EXTENT>
      <TAG>PER</TAG>
    </ANNOTATION>
    <ANNOTATION id="NW_OZO_UZB_031264_20140900-NE3" task="NE">
      <EXTENT start_char="311" end_char="330">Botirbek Eshqoʻziyev</EXTENT>
      <TAG>PER</TAG>
    </ANNOTATION>
    <ANNOTATION id="NW_OZO_UZB_031264_20140900-NE4" task="NE">
      <EXTENT start_char="346" end_char="382">Oʻzbekiston Milliy xavfsizlik xizmati</EXTENT>
      <TAG>ORG</TAG>
    </ANNOTATION>
    <ANNOTATION id="NW_OZO_UZB_031264_20140900-NE5" task="NE">
      <EXTENT start_char="69" end_char="82">Toshkent shaha</EXTENT>
      <TAG>LOC</TAG>
    </ANNOTATION>
    <ANNOTATION id="NW_OZO_UZB_031264_20140900-NE6" task="NE">
      <EXTENT start_char="89" end_char="128">Oʻzbekiston Yoshlar intellektual markazi</EXTENT>
      <TAG>ORG</TAG>
    </ANNOTATION>
    <ANNOTATION id="NW_OZO_UZB_031264_20140900-NE7" task="NE">
      <EXTENT start_char="142" end_char="163">Sharq Prizma” jamiyati</EXTENT>
      <TAG>ORG</TAG>
    </ANNOTATION>
    <ANNOTATION id="NW_OZO_UZB_031264_20140900-NE8" task="NE">
      <EXTENT start_char="236" end_char="251">Bahrom Ibragimov</EXTENT>
      <TAG>PER</TAG>
    </ANNOTATION>
    <ANNOTATION id="NW_OZO_UZB_031264_20140900-NE9" task="NE">
      <EXTENT start_char="254" end_char="268">Davron Kabilov,</EXTENT>
      <TAG>PER</TAG>
    </ANNOTATION>
    <ANNOTATION id="NW_OZO_UZB_031264_20140900-NE10" task="NE">
      <EXTENT start_char="224" end_char="231">xodimlar</EXTENT>
      <TAG>TTL</TAG>
    </ANNOTATION>
    <ANNOTATION id="NW_OZO_UZB_031264_20140900-NE11" task="NE">
      <EXTENT start_char="443" end_char="453">Oʻzbekiston</EXTENT>
      <TAG>LOC</TAG>
    </ANNOTATION>
    <ANNOTATION id="NW_OZO_UZB_031264_20140900-NE12" task="NE">
      <EXTENT start_char="619" end_char="634">Bahrom Ibragimov</EXTENT>
      <TAG>PER</TAG>
    </ANNOTATION>
    <ANNOTATION id="NW_OZO_UZB_031264_20140900-NE13" task="NE">
      <EXTENT start_char="646" end_char="652">Bahodir</EXTENT>
      <TAG>PER</TAG>
    </ANNOTATION>
    <ANNOTATION id="NW_OZO_UZB_031264_20140900-NE14" task="NE">
      <EXTENT start_char="747" end_char="752">Ayblov</EXTENT>
      <TAG>PER</TAG>
    </ANNOTATION>
    <ANNOTATION id="NW_OZO_UZB_031264_20140900-NE15" task="NE">
      <EXTENT start_char="1033" end_char="1039">Bahodir</EXTENT>
      <TAG>PER</TAG>
    </ANNOTATION>
    <ANNOTATION id="NW_OZO_UZB_031264_20140900-NE16" task="NE">
      <EXTENT start_char="1043" end_char="1048">Ayblov</EXTENT>
      <TAG>PER</TAG>
    </ANNOTATION>
    <ANNOTATION id="NW_OZO_UZB_031264_20140900-NE17" task="NE">
      <EXTENT start_char="1083" end_char="1089">Turkiya</EXTENT>
      <TAG>LOC</TAG>
    </ANNOTATION>
    <ANNOTATION id="NW_OZO_UZB_031264_20140900-NE18" task="NE">
      <EXTENT start_char="1096" end_char="1131">Nurchilar” diniy maʼrifiy tashkiloti</EXTENT>
      <TAG>ORG</TAG>
    </ANNOTATION>
    <ANNOTATION id="NW_OZO_UZB_031264_20140900-NE19" task="NE">
      <EXTENT start_char="1263" end_char="1292">Oʻzbekiston Vazirlar Mahkamasi</EXTENT>
      <TAG>ORG</TAG>
    </ANNOTATION>
    <ANNOTATION id="NW_OZO_UZB_031264_20140900-NE20" task="NE">
      <EXTENT start_char="1304" end_char="1325">Diniy ishlar qoʻmitasi</EXTENT>
      <TAG>ORG</TAG>
    </ANNOTATION>
    <ANNOTATION id="NW_OZO_UZB_031264_20140900-NE21" task="NE">
      <EXTENT start_char="1494" end_char="1509">Bahrom Ibragimov</EXTENT>
      <TAG>PER</TAG>
    </ANNOTATION>
    <ANNOTATION id="NW_OZO_UZB_031264_20140900-NE22" task="NE">
      <EXTENT start_char="1521" end_char="1527">Bahodir</EXTENT>
      <TAG>PER</TAG>
    </ANNOTATION>
    <ANNOTATION id="NW_OZO_UZB_031264_20140900-NE23" task="NE">
      <EXTENT start_char="1560" end_char="1583">Oʻzbekiston respublikasi</EXTENT>
      <TAG>LOC</TAG>
    </ANNOTATION>
    <ANNOTATION id="NW_OZO_UZB_031264_20140900-NE24" task="NE">
      <EXTENT start_char="1588" end_char="1609">Nurchilar” diniy oqimi</EXTENT>
      <TAG>ORG</TAG>
    </ANNOTATION>
    <ANNOTATION id="NW_OZO_UZB_031264_20140900-NE25" task="NE">
      <EXTENT start_char="1642" end_char="1654">Shahobiddinov</EXTENT>
      <TAG>PER</TAG>
    </ANNOTATION>
    <ANNOTATION id="NW_OZO_UZB_031264_20140900-NE26" task="NE">
      <EXTENT start_char="1815" end_char="1823">Nurchilar</EXTENT>
      <TAG>ORG</TAG>
    </ANNOTATION>
    <ANNOTATION id="NW_OZO_UZB_031264_20140900-NE27" task="NE">
      <EXTENT start_char="1966" end_char="1972">Bahodir</EXTENT>
      <TAG>PER</TAG>
    </ANNOTATION>
    <ANNOTATION id="NW_OZO_UZB_031264_20140900-NE28" task="NE">
      <EXTENT start_char="2009" end_char="2019">Oʻzbekiston</EXTENT>
      <TAG>LOC</TAG>
    </ANNOTATION>
    <ANNOTATION id="NW_OZO_UZB_031264_20140900-NE29" task="NE">
      <EXTENT start_char="2139" end_char="2149">Oʻzbekiston</EXTENT>
      <TAG>LOC</TAG>
    </ANNOTATION>
    <ANNOTATION id="NW_OZO_UZB_031264_20140900-NE30" task="NE">
      <EXTENT start_char="2506" end_char="2512">Bahodir</EXTENT>
      <TAG>PER</TAG>
    </ANNOTATION>
    <ANNOTATION id="NW_OZO_UZB_031264_20140900-NE31" task="NE">
      <EXTENT start_char="2988" end_char="2994">Angliya</EXTENT>
      <TAG>LOC</TAG>
    </ANNOTATION>
    <ANNOTATION id="NW_OZO_UZB_031264_20140900-NE32" task="NE">
      <EXTENT start_char="2999" end_char="3005">Amerika</EXTENT>
      <TAG>LOC</TAG>
    </ANNOTATION>
    <ANNOTATION id="NW_OZO_UZB_031264_20140900-NE33" task="NE">
      <EXTENT start_char="3054" end_char="3061">Bahodir.</EXTENT>
      <TAG>PER</TAG>
    </ANNOTATION>
    <ANNOTATION id="NW_OZO_UZB_031264_20140900-NE34" task="NE">
      <EXTENT start_char="3222" end_char="3234">Hamza Jumayev</EXTENT>
      <TAG>PER</TAG>
    </ANNOTATION>
    <ANNOTATION id="NW_OZO_UZB_031264_20140900-NE35" task="NE">
      <EXTENT start_char="3213" end_char="3220">muharrir</EXTENT>
      <TAG>TTL</TAG>
    </ANNOTATION>
    <ANNOTATION id="NW_OZO_UZB_031264_20140900-NE36" task="NE">
      <EXTENT start_char="3290" end_char="3302">Hamza Jumayev</EXTENT>
      <TAG>PER</TAG>
    </ANNOTATION>
    <ANNOTATION id="NW_OZO_UZB_031264_20140900-NE37" task="NE">
      <EXTENT start_char="3402" end_char="3414">Hamza Jumayev</EXTENT>
      <TAG>PER</TAG>
    </ANNOTATION>
    <ANNOTATION id="NW_OZO_UZB_031264_20140900-NE38" task="NE">
      <EXTENT start_char="3494" end_char="3506">Hamza Jumayev</EXTENT>
      <TAG>PER</TAG>
    </ANNOTATION>
    <ANNOTATION id="NW_OZO_UZB_031264_20140900-NE39" task="NE">
      <EXTENT start_char="3510" end_char="3516">Jumayev</EXTENT>
      <TAG>PER</TAG>
    </ANNOTATION>
    <ANNOTATION id="NW_OZO_UZB_031264_20140900-NE40" task="NE">
      <EXTENT start_char="3740" end_char="3769">Oʻzbekiston Bosh Prokuraturasi</EXTENT>
      <TAG>ORG</TAG>
    </ANNOTATION>
    <ANNOTATION id="NW_OZO_UZB_031264_20140900-NE41" task="NE">
      <EXTENT start_char="3787" end_char="3794">boshligʻ</EXTENT>
      <TAG>TTL</TAG>
    </ANNOTATION>
    <ANNOTATION id="NW_OZO_UZB_031264_20140900-NE42" task="NE">
      <EXTENT start_char="3797" end_char="3813">Svetlana Ortiqova</EXTENT>
      <TAG>PER</TAG>
    </ANNOTATION>
    <ANNOTATION id="NW_OZO_UZB_031264_20140900-NE43" task="NE">
      <EXTENT start_char="4029" end_char="4045">Svetlana Ortiqova</EXTENT>
      <TAG>PER</TAG>
    </ANNOTATION>
    <ANNOTATION id="NW_OZO_UZB_031264_20140900-NE44" task="NE">
      <EXTENT start_char="4106" end_char="4125">Oʻzbekiston hukumati</EXTENT>
      <TAG>ORG</TAG>
    </ANNOTATION>
    <ANNOTATION id="NW_OZO_UZB_031264_20140900-NE45" task="NE">
      <EXTENT start_char="4178" end_char="4184">Turkiya</EXTENT>
      <TAG>LOC</TAG>
    </ANNOTATION>
    <ANNOTATION id="NW_OZO_UZB_031264_20140900-NE46" task="NE">
      <EXTENT start_char="4314" end_char="4333">Oʻzbekiston hukumati</EXTENT>
      <TAG>ORG</TAG>
    </ANNOTATION>
    <ANNOTATION id="NW_OZO_UZB_031264_20140900-NE47" task="NE">
      <EXTENT start_char="184" end_char="188">Irmoq</EXTENT>
      <TAG>ORG</TAG>
    </ANNOTATION>
    <ANNOTATION id="NW_OZO_UZB_031264_20140900-NE48" task="NE">
      <EXTENT start_char="203" end_char="212">Etti iqlim</EXTENT>
      <TAG>ORG</TAG>
    </ANNOTATION>
    <ANNOTATION id="NW_OZO_UZB_031264_20140900-NE49" task="NE">
      <EXTENT start_char="455" end_char="456">JK</EXTENT>
      <TAG>ORG</TAG>
    </ANNOTATION>
    <ANNOTATION id="NW_OZO_UZB_031264_20140900-NE50" task="NE">
      <EXTENT start_char="3136" end_char="3140">Irmoq</EXTENT>
      <TAG>ORG</TAG>
    </ANNOTATION>
    <ANNOTATION id="NW_OZO_UZB_031264_20140900-NE51" task="NE">
      <EXTENT start_char="3318" end_char="3320">MXX</EXTENT>
      <TAG>ORG</TAG>
    </ANNOTATION>
    <ANNOTATION id="NW_OZO_UZB_031264_20140900-NE52" task="NE">
      <EXTENT start_char="3923" end_char="3927">Irmoq</EXTENT>
      <TAG>ORG</TAG>
    </ANNOTATION>
  </DOC>
</LCTL_ANNOTATIONS>
